napari_kld/__init__.py
napari_kld/_reader.py
napari_kld/_sample_data.py
napari_kld/_version.py
napari_kld/_widget.py
napari_kld/_writer.py
napari_kld/baseww.py
napari_kld/napari.yaml
napari_kld/widgets.py
napari_kld/_tests/__init__.py
napari_kld/_tests/test_reader.py
napari_kld/_tests/test_sample_data.py
napari_kld/_tests/test_widget.py
napari_kld/_tests/test_writer.py
napari_kld/base/back_projector.py
napari_kld/base/deconvolution.py
napari_kld/base/generate_phantom.py
napari_kld/base/generate_synthetic_data.py
napari_kld/base/loss_functions.py
napari_kld/base/methods.py
napari_kld/base/predict.py
napari_kld/base/train.py
napari_kld/base/models/kernelnet.py
napari_kld/base/utils/dataset_utils.py
napari_kld/base/utils/evaluation.py
napari_kld-1.1.0.dist-info/LICENSE
napari_kld-1.1.0.dist-info/METADATA
napari_kld-1.1.0.dist-info/WHEEL
napari_kld-1.1.0.dist-info/entry_points.txt
napari_kld-1.1.0.dist-info/top_level.txt
napari_kld-1.1.0.dist-info/RECORD
