Metadata-Version: 2.1
Name: napari-kld
Version: 1.1.0
Summary: Kernel learning deconvolution (KLD) is a rapid deconvolution algorithm for fluorescence microscopic image, which learns the forward and backward kernels in Richardson-Lucy Deconvolution (KLD) from paired low-/high-resolution images. 
Author: Qiqi Lu
Author-email: 136303971@qq.com
License: 
Classifier: Development Status :: 2 - Pre-Alpha
Classifier: Framework :: napari
Classifier: Intended Audience :: Developers
Classifier: License :: OSI Approved :: BSD License
Classifier: Operating System :: OS Independent
Classifier: Programming Language :: Python
Classifier: Programming Language :: Python :: 3
Classifier: Programming Language :: Python :: 3 :: Only
Classifier: Programming Language :: Python :: 3.9
Classifier: Programming Language :: Python :: 3.10
Classifier: Programming Language :: Python :: 3.11
Classifier: Programming Language :: Python :: 3.12
Classifier: Topic :: Scientific/Engineering :: Image Processing
Requires-Python: >=3.9
License-File: LICENSE
Requires-Dist: numpy==1.26.4
Requires-Dist: magicgui
Requires-Dist: qtpy
Requires-Dist: scikit-image
Requires-Dist: torch==2.0
Requires-Dist: torchvision
Requires-Dist: fft-conv-pytorch
Requires-Dist: pytorch-msssim
Requires-Dist: tensorboard
Requires-Dist: pydicom
Provides-Extra: testing
Requires-Dist: tox; extra == "testing"
Requires-Dist: pytest; extra == "testing"
Requires-Dist: pytest-cov; extra == "testing"
Requires-Dist: pytest-qt; extra == "testing"
Requires-Dist: napari; extra == "testing"
Requires-Dist: pyqt5; extra == "testing"
